cashaccount/__init__.py
cashaccount/cli.py
cashaccount/payment.py
cashaccount/registration.py
test/__init__.py
test/test_payment.py
test/test_registration.py
pycashaccount-0.3.2.dist-info/LICENSE
pycashaccount-0.3.2.dist-info/METADATA
pycashaccount-0.3.2.dist-info/WHEEL
pycashaccount-0.3.2.dist-info/entry_points.txt
pycashaccount-0.3.2.dist-info/top_level.txt
pycashaccount-0.3.2.dist-info/RECORD
