Metadata-Version: 2.1
Name: pycashaccount
Version: 0.3.2
Summary: helper for creating cash accounts
Home-page: https://github.com/emergent-reasons/pycashaccount
Author: emergent-reasons
Author-email: emergentreasons@gmail.com
License: UNKNOWN
Platform: UNKNOWN
Classifier: Programming Language :: Python :: 3
Classifier: License :: OSI Approved :: MIT License
Classifier: Operating System :: OS Independent
Requires-Dist: base58
Requires-Dist: cashaddress
Requires-Dist: click
